<?xml version="1.0" encoding="UTF-8"?>
<resourceUtilization>
  <configuration>
    <time_unit>SECONDS</time_unit>
  </configuration>
  <processes>
    <process>
      <id>sid-f1827831-d6c7-4585-84df-57e0fb21ae2f</id>
      <cost>
        <min>3.375</min>
        <max>57.18055555555555</max>
        <median>36.22222222222222</median>
        <Q1>19.90277777777778</Q1>
        <Q3>46.15277777777777</Q3>
        <avg>33.848710317460316</avg>
        <total>947.7638888888888</total>
      </cost>
      <time>
        <flow_time>
          <min>7477.0</min>
          <max>65436.0</max>
          <median>11145.0</median>
          <Q1>9553.0</Q1>
          <Q3>30685.0</Q3>
          <avg>19475.75</avg>
          <total>545321.0</total>
        </flow_time>
        <effective>
          <min>6760.0</min>
          <max>11780.0</max>
          <median>9458.0</median>
          <Q1>8663.0</Q1>
          <Q3>10789.0</Q3>
          <avg>9631.0</avg>
          <total>269668.0</total>
        </effective>
        <waiting>
          <min>0.0</min>
          <max>29376.0</max>
          <median>1264.0</median>
          <Q1>672.0</Q1>
          <Q3>12457.0</Q3>
          <avg>7916.178571428572</avg>
          <total>221653.0</total>
        </waiting>
        <off_timetable>
          <min>0.0</min>
          <max>54000.0</max>
          <median>0.0</median>
          <Q1>0.0</Q1>
          <Q3>0.0</Q3>
          <avg>1928.5714285714287</avg>
          <total>54000.0</total>
        </off_timetable>
      </time>
      <instances>
        <instance>
          <costs>47.01388888888888</costs>
          <time>
            <duration>13393</duration>
            <effective>11107</effective>
            <waiting>2286</waiting>
            <offTime>0</offTime>
          </time>
        </instance>
        <instance>
          <costs>13.763888888888888</costs>
          <time>
            <duration>9818</duration>
            <effective>8713</effective>
            <waiting>1105</waiting>
            <offTime>0</offTime>
          </time>
        </instance>
        <instance>
          <costs>39.583333333333336</costs>
          <time>
            <duration>11145</duration>
            <effective>10155</effective>
            <waiting>990</waiting>
            <offTime>0</offTime>
          </time>
        </instance>
        <instance>
          <costs>13.861111111111109</costs>
          <time>
            <duration>8809</duration>
            <effective>8303</effective>
            <waiting>506</waiting>
            <offTime>0</offTime>
          </time>
        </instance>
        <instance>
          <costs>22.0</costs>
          <time>
            <duration>9928</duration>
            <effective>9239</effective>
            <waiting>689</waiting>
            <offTime>0</offTime>
          </time>
        </instance>
        <instance>
          <costs>31.43055555555555</costs>
          <time>
            <duration>9553</duration>
            <effective>9553</effective>
            <waiting>0</waiting>
            <offTime>0</offTime>
          </time>
        </instance>
        <instance>
          <costs>21.333333333333332</costs>
          <time>
            <duration>10086</duration>
            <effective>8822</effective>
            <waiting>1264</waiting>
            <offTime>0</offTime>
          </time>
        </instance>
        <instance>
          <costs>51.30555555555556</costs>
          <time>
            <duration>13323</duration>
            <effective>11416</effective>
            <waiting>1907</waiting>
            <offTime>0</offTime>
          </time>
        </instance>
        <instance>
          <costs>16.52777777777778</costs>
          <time>
            <duration>9524</duration>
            <effective>8663</effective>
            <waiting>861</waiting>
            <offTime>0</offTime>
          </time>
        </instance>
        <instance>
          <costs>19.90277777777778</costs>
          <time>
            <duration>9341</duration>
            <effective>8752</effective>
            <waiting>589</waiting>
            <offTime>0</offTime>
          </time>
        </instance>
        <instance>
          <costs>39.27777777777778</costs>
          <time>
            <duration>9122</duration>
            <effective>8828</effective>
            <waiting>294</waiting>
            <offTime>0</offTime>
          </time>
        </instance>
        <instance>
          <costs>38.34722222222222</costs>
          <time>
            <duration>10453</duration>
            <effective>8866</effective>
            <waiting>1587</waiting>
            <offTime>0</offTime>
          </time>
        </instance>
        <instance>
          <costs>41.625</costs>
          <time>
            <duration>11498</duration>
            <effective>10850</effective>
            <waiting>648</waiting>
            <offTime>0</offTime>
          </time>
        </instance>
        <instance>
          <costs>55.30555555555554</costs>
          <time>
            <duration>11109</duration>
            <effective>10437</effective>
            <waiting>672</waiting>
            <offTime>0</offTime>
          </time>
        </instance>
        <instance>
          <costs>3.375</costs>
          <time>
            <duration>8324</duration>
            <effective>7648</effective>
            <waiting>676</waiting>
            <offTime>0</offTime>
          </time>
        </instance>
        <instance>
          <costs>10.555555555555555</costs>
          <time>
            <duration>7477</duration>
            <effective>6760</effective>
            <waiting>717</waiting>
            <offTime>0</offTime>
          </time>
        </instance>
        <instance>
          <costs>21.138888888888886</costs>
          <time>
            <duration>9930</duration>
            <effective>7612</effective>
            <waiting>2318</waiting>
            <offTime>0</offTime>
          </time>
        </instance>
        <instance>
          <costs>46.15277777777777</costs>
          <time>
            <duration>40354</duration>
            <effective>10978</effective>
            <waiting>29376</waiting>
            <offTime>0</offTime>
          </time>
        </instance>
        <instance>
          <costs>16.333333333333332</costs>
          <time>
            <duration>36670</duration>
            <effective>8598</effective>
            <waiting>28072</waiting>
            <offTime>0</offTime>
          </time>
        </instance>
        <instance>
          <costs>30.11111111111111</costs>
          <time>
            <duration>38467</duration>
            <effective>9458</effective>
            <waiting>29009</waiting>
            <offTime>0</offTime>
          </time>
        </instance>
        <instance>
          <costs>57.18055555555555</costs>
          <time>
            <duration>65436</duration>
            <effective>11436</effective>
            <waiting>0</waiting>
            <offTime>54000</offTime>
          </time>
        </instance>
        <instance>
          <costs>52.15277777777778</costs>
          <time>
            <duration>37189</duration>
            <effective>11041</effective>
            <waiting>26148</waiting>
            <offTime>0</offTime>
          </time>
        </instance>
        <instance>
          <costs>51.875</costs>
          <time>
            <duration>34007</duration>
            <effective>11780</effective>
            <waiting>22227</waiting>
            <offTime>0</offTime>
          </time>
        </instance>
        <instance>
          <costs>46.055555555555564</costs>
          <time>
            <duration>30685</duration>
            <effective>10789</effective>
            <waiting>19896</waiting>
            <offTime>0</offTime>
          </time>
        </instance>
        <instance>
          <costs>48.111111111111114</costs>
          <time>
            <duration>30691</duration>
            <effective>10669</effective>
            <waiting>20022</waiting>
            <offTime>0</offTime>
          </time>
        </instance>
        <instance>
          <costs>41.291666666666664</costs>
          <time>
            <duration>23152</duration>
            <effective>10695</effective>
            <waiting>12457</waiting>
            <offTime>0</offTime>
          </time>
        </instance>
        <instance>
          <costs>35.93055555555556</costs>
          <time>
            <duration>17256</duration>
            <effective>8587</effective>
            <waiting>8669</waiting>
            <offTime>0</offTime>
          </time>
        </instance>
        <instance>
          <costs>36.22222222222222</costs>
          <time>
            <duration>18581</duration>
            <effective>9913</effective>
            <waiting>8668</waiting>
            <offTime>0</offTime>
          </time>
        </instance>
      </instances>
      <activities>
        <activity>
          <id>67</id>
          <name>Instrumental normal</name>
          <cost>
            <min>0.0</min>
            <max>0.0</max>
            <median>0.0</median>
            <Q1>0.0</Q1>
            <Q3>0.0</Q3>
            <avg>0.0</avg>
            <total>0.0</total>
          </cost>
          <time>
            <duration>
              <min>3600.0</min>
              <max>3600.0</max>
              <median>3600.0</median>
              <Q1>3600.0</Q1>
              <Q3>3600.0</Q3>
              <avg>3600.0</avg>
              <total>79200.0</total>
            </duration>
            <waiting>
              <min>0.0</min>
              <max>0.0</max>
              <median>0.0</median>
              <Q1>0.0</Q1>
              <Q3>0.0</Q3>
              <avg>0.0</avg>
              <total>0.0</total>
            </waiting>
            <resources_idle>
              <min>0.0</min>
              <max>0.0</max>
              <median>0.0</median>
              <Q1>0.0</Q1>
              <Q3>0.0</Q3>
              <avg>0.0</avg>
              <total>0.0</total>
            </resources_idle>
          </time>
          <instances>
            <instance>
              <cost>0.0</cost>
              <time>
                <effective>3600</effective>
                <waiting>0</waiting>
                <resources_idle>0</resources_idle>
              </time>
            </instance>
            <instance>
              <cost>0.0</cost>
              <time>
                <effective>3600</effective>
                <waiting>0</waiting>
                <resources_idle>0</resources_idle>
              </time>
            </instance>
            <instance>
              <cost>0.0</cost>
              <time>
                <effective>3600</effective>
                <waiting>0</waiting>
                <resources_idle>0</resources_idle>
              </time>
            </instance>
            <instance>
              <cost>0.0</cost>
              <time>
                <effective>3600</effective>
                <waiting>0</waiting>
                <resources_idle>0</resources_idle>
              </time>
            </instance>
            <instance>
              <cost>0.0</cost>
              <time>
                <effective>3600</effective>
                <waiting>0</waiting>
                <resources_idle>0</resources_idle>
              </time>
            </instance>
            <instance>
              <cost>0.0</cost>
              <time>
                <effective>3600</effective>
                <waiting>0</waiting>
                <resources_idle>0</resources_idle>
              </time>
            </instance>
            <instance>
              <cost>0.0</cost>
              <time>
                <effective>3600</effective>
                <waiting>0</waiting>
                <resources_idle>0</resources_idle>
              </time>
            </instance>
            <instance>
              <cost>0.0</cost>
              <time>
                <effective>3600</effective>
                <waiting>0</waiting>
                <resources_idle>0</resources_idle>
              </time>
            </instance>
            <instance>
              <cost>0.0</cost>
              <time>
                <effective>3600</effective>
                <waiting>0</waiting>
                <resources_idle>0</resources_idle>
              </time>
            </instance>
            <instance>
              <cost>0.0</cost>
              <time>
                <effective>3600</effective>
                <waiting>0</waiting>
                <resources_idle>0</resources_idle>
              </time>
            </instance>
            <instance>
              <cost>0.0</cost>
              <time>
                <effective>3600</effective>
                <waiting>0</waiting>
                <resources_idle>0</resources_idle>
              </time>
            </instance>
            <instance>
              <cost>0.0</cost>
              <time>
                <effective>3600</effective>
                <waiting>0</waiting>
                <resources_idle>0</resources_idle>
              </time>
            </instance>
            <instance>
              <cost>0.0</cost>
              <time>
                <effective>3600</effective>
                <waiting>0</waiting>
                <resources_idle>0</resources_idle>
              </time>
            </instance>
            <instance>
              <cost>0.0</cost>
              <time>
                <effective>3600</effective>
                <waiting>0</waiting>
                <resources_idle>0</resources_idle>
              </time>
            </instance>
            <instance>
              <cost>0.0</cost>
              <time>
                <effective>3600</effective>
                <waiting>0</waiting>
                <resources_idle>0</resources_idle>
              </time>
            </instance>
            <instance>
              <cost>0.0</cost>
              <time>
                <effective>3600</effective>
                <waiting>0</waiting>
                <resources_idle>0</resources_idle>
              </time>
            </instance>
            <instance>
              <cost>0.0</cost>
              <time>
                <effective>3600</effective>
                <waiting>0</waiting>
                <resources_idle>0</resources_idle>
              </time>
            </instance>
            <instance>
              <cost>0.0</cost>
              <time>
                <effective>3600</effective>
                <waiting>0</waiting>
                <resources_idle>0</resources_idle>
              </time>
            </instance>
            <instance>
              <cost>0.0</cost>
              <time>
                <effective>3600</effective>
                <waiting>0</waiting>
                <resources_idle>0</resources_idle>
              </time>
            </instance>
            <instance>
              <cost>0.0</cost>
              <time>
                <effective>3600</effective>
                <waiting>0</waiting>
                <resources_idle>0</resources_idle>
              </time>
            </instance>
            <instance>
              <cost>0.0</cost>
              <time>
                <effective>3600</effective>
                <waiting>0</waiting>
                <resources_idle>0</resources_idle>
              </time>
            </instance>
            <instance>
              <cost>0.0</cost>
              <time>
                <effective>3600</effective>
                <waiting>0</waiting>
                <resources_idle>0</resources_idle>
              </time>
            </instance>
          </instances>
        </activity>
        <activity>
          <id>78</id>
          <name>Composición de cargas</name>
          <cost>
            <min>0.0</min>
            <max>6.180555555555555</max>
            <median>3.444444444444444</median>
            <Q1>2.347222222222222</Q1>
            <Q3>4.5</Q3>
            <avg>3.5376984126984135</avg>
            <total>99.05555555555557</total>
          </cost>
          <time>
            <duration>
              <min>0.0</min>
              <max>445.0</max>
              <median>248.0</median>
              <Q1>169.0</Q1>
              <Q3>324.0</Q3>
              <avg>254.71428571428572</avg>
              <total>7132.0</total>
            </duration>
            <waiting>
              <min>0.0</min>
              <max>0.0</max>
              <median>0.0</median>
              <Q1>0.0</Q1>
              <Q3>0.0</Q3>
              <avg>0.0</avg>
              <total>0.0</total>
            </waiting>
            <resources_idle>
              <min>0.0</min>
              <max>0.0</max>
              <median>0.0</median>
              <Q1>0.0</Q1>
              <Q3>0.0</Q3>
              <avg>0.0</avg>
              <total>0.0</total>
            </resources_idle>
          </time>
          <instances>
            <instance>
              <cost>2.833333333333333</cost>
              <time>
                <effective>204</effective>
                <waiting>0</waiting>
                <resources_idle>0</resources_idle>
              </time>
            </instance>
            <instance>
              <cost>5.416666666666666</cost>
              <time>
                <effective>390</effective>
                <waiting>0</waiting>
                <resources_idle>0</resources_idle>
              </time>
            </instance>
            <instance>
              <cost>5.166666666666666</cost>
              <time>
                <effective>372</effective>
                <waiting>0</waiting>
                <resources_idle>0</resources_idle>
              </time>
            </instance>
            <instance>
              <cost>4.194444444444445</cost>
              <time>
                <effective>302</effective>
                <waiting>0</waiting>
                <resources_idle>0</resources_idle>
              </time>
            </instance>
            <instance>
              <cost>4.444444444444445</cost>
              <time>
                <effective>320</effective>
                <waiting>0</waiting>
                <resources_idle>0</resources_idle>
              </time>
            </instance>
            <instance>
              <cost>3.444444444444444</cost>
              <time>
                <effective>248</effective>
                <waiting>0</waiting>
                <resources_idle>0</resources_idle>
              </time>
            </instance>
            <instance>
              <cost>2.4027777777777777</cost>
              <time>
                <effective>173</effective>
                <waiting>0</waiting>
                <resources_idle>0</resources_idle>
              </time>
            </instance>
            <instance>
              <cost>4.916666666666666</cost>
              <time>
                <effective>354</effective>
                <waiting>0</waiting>
                <resources_idle>0</resources_idle>
              </time>
            </instance>
            <instance>
              <cost>3.4027777777777777</cost>
              <time>
                <effective>245</effective>
                <waiting>0</waiting>
                <resources_idle>0</resources_idle>
              </time>
            </instance>
            <instance>
              <cost>4.055555555555555</cost>
              <time>
                <effective>292</effective>
                <waiting>0</waiting>
                <resources_idle>0</resources_idle>
              </time>
            </instance>
            <instance>
              <cost>5.430555555555555</cost>
              <time>
                <effective>391</effective>
                <waiting>0</waiting>
                <resources_idle>0</resources_idle>
              </time>
            </instance>
            <instance>
              <cost>4.666666666666666</cost>
              <time>
                <effective>336</effective>
                <waiting>0</waiting>
                <resources_idle>0</resources_idle>
              </time>
            </instance>
            <instance>
              <cost>2.3055555555555554</cost>
              <time>
                <effective>166</effective>
                <waiting>0</waiting>
                <resources_idle>0</resources_idle>
              </time>
            </instance>
            <instance>
              <cost>0.0</cost>
              <time>
                <effective>0</effective>
                <waiting>0</waiting>
                <resources_idle>0</resources_idle>
              </time>
            </instance>
            <instance>
              <cost>2.833333333333333</cost>
              <time>
                <effective>204</effective>
                <waiting>0</waiting>
                <resources_idle>0</resources_idle>
              </time>
            </instance>
            <instance>
              <cost>2.1666666666666665</cost>
              <time>
                <effective>156</effective>
                <waiting>0</waiting>
                <resources_idle>0</resources_idle>
              </time>
            </instance>
            <instance>
              <cost>1.736111111111111</cost>
              <time>
                <effective>125</effective>
                <waiting>0</waiting>
                <resources_idle>0</resources_idle>
              </time>
            </instance>
            <instance>
              <cost>1.7916666666666665</cost>
              <time>
                <effective>129</effective>
                <waiting>0</waiting>
                <resources_idle>0</resources_idle>
              </time>
            </instance>
            <instance>
              <cost>4.236111111111111</cost>
              <time>
                <effective>305</effective>
                <waiting>0</waiting>
                <resources_idle>0</resources_idle>
              </time>
            </instance>
            <instance>
              <cost>2.5277777777777777</cost>
              <time>
                <effective>182</effective>
                <waiting>0</waiting>
                <resources_idle>0</resources_idle>
              </time>
            </instance>
            <instance>
              <cost>4.444444444444445</cost>
              <time>
                <effective>320</effective>
                <waiting>0</waiting>
                <resources_idle>0</resources_idle>
              </time>
            </instance>
            <instance>
              <cost>5.430555555555555</cost>
              <time>
                <effective>391</effective>
                <waiting>0</waiting>
                <resources_idle>0</resources_idle>
              </time>
            </instance>
            <instance>
              <cost>6.180555555555555</cost>
              <time>
                <effective>445</effective>
                <waiting>0</waiting>
                <resources_idle>0</resources_idle>
              </time>
            </instance>
            <instance>
              <cost>1.347222222222222</cost>
              <time>
                <effective>97</effective>
                <waiting>0</waiting>
                <resources_idle>0</resources_idle>
              </time>
            </instance>
            <instance>
              <cost>2.347222222222222</cost>
              <time>
                <effective>169</effective>
                <waiting>0</waiting>
                <resources_idle>0</resources_idle>
              </time>
            </instance>
            <instance>
              <cost>4.5</cost>
              <time>
                <effective>324</effective>
                <waiting>0</waiting>
                <resources_idle>0</resources_idle>
              </time>
            </instance>
            <instance>
              <cost>2.6805555555555554</cost>
              <time>
                <effective>193</effective>
                <waiting>0</waiting>
                <resources_idle>0</resources_idle>
              </time>
            </instance>
            <instance>
              <cost>4.152777777777778</cost>
              <time>
                <effective>299</effective>
                <waiting>0</waiting>
                <resources_idle>0</resources_idle>
              </time>
            </instance>
          </instances>
        </activity>
        <activity>
          <id>69</id>
          <name>Priones</name>
          <cost>
            <min>0.0</min>
            <max>0.0</max>
            <median>0.0</median>
            <Q1>0.0</Q1>
            <Q3>0.0</Q3>
            <avg>0.0</avg>
            <total>0.0</total>
          </cost>
          <time>
            <duration>
              <min>3600.0</min>
              <max>3600.0</max>
              <median>3600.0</median>
              <Q1>3600.0</Q1>
              <Q3>3600.0</Q3>
              <avg>3600.0</avg>
              <total>10800.0</total>
            </duration>
            <waiting>
              <min>0.0</min>
              <max>0.0</max>
              <median>0.0</median>
              <Q1>0.0</Q1>
              <Q3>0.0</Q3>
              <avg>0.0</avg>
              <total>0.0</total>
            </waiting>
            <resources_idle>
              <min>0.0</min>
              <max>0.0</max>
              <median>0.0</median>
              <Q1>0.0</Q1>
              <Q3>0.0</Q3>
              <avg>0.0</avg>
              <total>0.0</total>
            </resources_idle>
          </time>
          <instances>
            <instance>
              <cost>0.0</cost>
              <time>
                <effective>3600</effective>
                <waiting>0</waiting>
                <resources_idle>0</resources_idle>
              </time>
            </instance>
            <instance>
              <cost>0.0</cost>
              <time>
                <effective>3600</effective>
                <waiting>0</waiting>
                <resources_idle>0</resources_idle>
              </time>
            </instance>
            <instance>
              <cost>0.0</cost>
              <time>
                <effective>3600</effective>
                <waiting>0</waiting>
                <resources_idle>0</resources_idle>
              </time>
            </instance>
          </instances>
        </activity>
        <activity>
          <id>4</id>
          <name>INTRUM</name>
          <cost>
            <min>0.0</min>
            <max>0.0</max>
            <median>0.0</median>
            <Q1>0.0</Q1>
            <Q3>0.0</Q3>
            <avg>0.0</avg>
            <total>0.0</total>
          </cost>
          <time>
            <duration>
              <min>3605.0</min>
              <max>4445.0</max>
              <median>3805.0</median>
              <Q1>3690.0</Q1>
              <Q3>4055.0</Q3>
              <avg>3898.3333333333335</avg>
              <total>46780.0</total>
            </duration>
            <waiting>
              <min>0.0</min>
              <max>0.0</max>
              <median>0.0</median>
              <Q1>0.0</Q1>
              <Q3>0.0</Q3>
              <avg>0.0</avg>
              <total>0.0</total>
            </waiting>
            <resources_idle>
              <min>0.0</min>
              <max>0.0</max>
              <median>0.0</median>
              <Q1>0.0</Q1>
              <Q3>0.0</Q3>
              <avg>0.0</avg>
              <total>0.0</total>
            </resources_idle>
          </time>
          <instances>
            <instance>
              <cost>0.0</cost>
              <time>
                <effective>4445</effective>
                <waiting>0</waiting>
                <resources_idle>0</resources_idle>
              </time>
            </instance>
            <instance>
              <cost>0.0</cost>
              <time>
                <effective>3690</effective>
                <waiting>0</waiting>
                <resources_idle>0</resources_idle>
              </time>
            </instance>
            <instance>
              <cost>0.0</cost>
              <time>
                <effective>3605</effective>
                <waiting>0</waiting>
                <resources_idle>0</resources_idle>
              </time>
            </instance>
            <instance>
              <cost>0.0</cost>
              <time>
                <effective>3686</effective>
                <waiting>0</waiting>
                <resources_idle>0</resources_idle>
              </time>
            </instance>
            <instance>
              <cost>0.0</cost>
              <time>
                <effective>4253</effective>
                <waiting>0</waiting>
                <resources_idle>0</resources_idle>
              </time>
            </instance>
            <instance>
              <cost>0.0</cost>
              <time>
                <effective>4122</effective>
                <waiting>0</waiting>
                <resources_idle>0</resources_idle>
              </time>
            </instance>
            <instance>
              <cost>0.0</cost>
              <time>
                <effective>3705</effective>
                <waiting>0</waiting>
                <resources_idle>0</resources_idle>
              </time>
            </instance>
            <instance>
              <cost>0.0</cost>
              <time>
                <effective>3719</effective>
                <waiting>0</waiting>
                <resources_idle>0</resources_idle>
              </time>
            </instance>
            <instance>
              <cost>0.0</cost>
              <time>
                <effective>3873</effective>
                <waiting>0</waiting>
                <resources_idle>0</resources_idle>
              </time>
            </instance>
            <instance>
              <cost>0.0</cost>
              <time>
                <effective>3805</effective>
                <waiting>0</waiting>
                <resources_idle>0</resources_idle>
              </time>
            </instance>
            <instance>
              <cost>0.0</cost>
              <time>
                <effective>3822</effective>
                <waiting>0</waiting>
                <resources_idle>0</resources_idle>
              </time>
            </instance>
            <instance>
              <cost>0.0</cost>
              <time>
                <effective>4055</effective>
                <waiting>0</waiting>
                <resources_idle>0</resources_idle>
              </time>
            </instance>
          </instances>
        </activity>
        <activity>
          <id>5</id>
          <name>GOMAS</name>
          <cost>
            <min>0.0</min>
            <max>0.0</max>
            <median>0.0</median>
            <Q1>0.0</Q1>
            <Q3>0.0</Q3>
            <avg>0.0</avg>
            <total>0.0</total>
          </cost>
          <time>
            <duration>
              <min>3705.0</min>
              <max>4122.0</max>
              <median>3705.0</median>
              <Q1>3705.0</Q1>
              <Q3>4122.0</Q3>
              <avg>3913.5</avg>
              <total>7827.0</total>
            </duration>
            <waiting>
              <min>0.0</min>
              <max>0.0</max>
              <median>0.0</median>
              <Q1>0.0</Q1>
              <Q3>0.0</Q3>
              <avg>0.0</avg>
              <total>0.0</total>
            </waiting>
            <resources_idle>
              <min>0.0</min>
              <max>0.0</max>
              <median>0.0</median>
              <Q1>0.0</Q1>
              <Q3>0.0</Q3>
              <avg>0.0</avg>
              <total>0.0</total>
            </resources_idle>
          </time>
          <instances>
            <instance>
              <cost>0.0</cost>
              <time>
                <effective>4122</effective>
                <waiting>0</waiting>
                <resources_idle>0</resources_idle>
              </time>
            </instance>
            <instance>
              <cost>0.0</cost>
              <time>
                <effective>3705</effective>
                <waiting>0</waiting>
                <resources_idle>0</resources_idle>
              </time>
            </instance>
          </instances>
        </activity>
        <activity>
          <id>6</id>
          <name>CONTENE</name>
          <cost>
            <min>0.0</min>
            <max>0.0</max>
            <median>0.0</median>
            <Q1>0.0</Q1>
            <Q3>0.0</Q3>
            <avg>0.0</avg>
            <total>0.0</total>
          </cost>
          <time>
            <duration>
              <min>3690.0</min>
              <max>4122.0</max>
              <median>3705.0</median>
              <Q1>3690.0</Q1>
              <Q3>4055.0</Q3>
              <avg>3893.0</avg>
              <total>15572.0</total>
            </duration>
            <waiting>
              <min>0.0</min>
              <max>0.0</max>
              <median>0.0</median>
              <Q1>0.0</Q1>
              <Q3>0.0</Q3>
              <avg>0.0</avg>
              <total>0.0</total>
            </waiting>
            <resources_idle>
              <min>0.0</min>
              <max>0.0</max>
              <median>0.0</median>
              <Q1>0.0</Q1>
              <Q3>0.0</Q3>
              <avg>0.0</avg>
              <total>0.0</total>
            </resources_idle>
          </time>
          <instances>
            <instance>
              <cost>0.0</cost>
              <time>
                <effective>3690</effective>
                <waiting>0</waiting>
                <resources_idle>0</resources_idle>
              </time>
            </instance>
            <instance>
              <cost>0.0</cost>
              <time>
                <effective>3705</effective>
                <waiting>0</waiting>
                <resources_idle>0</resources_idle>
              </time>
            </instance>
            <instance>
              <cost>0.0</cost>
              <time>
                <effective>4055</effective>
                <waiting>0</waiting>
                <resources_idle>0</resources_idle>
              </time>
            </instance>
            <instance>
              <cost>0.0</cost>
              <time>
                <effective>4122</effective>
                <waiting>0</waiting>
                <resources_idle>0</resources_idle>
              </time>
            </instance>
          </instances>
        </activity>
        <activity>
          <id>7</id>
          <name>PRIONES</name>
          <cost>
            <min>0.0</min>
            <max>0.0</max>
            <median>0.0</median>
            <Q1>0.0</Q1>
            <Q3>0.0</Q3>
            <avg>0.0</avg>
            <total>0.0</total>
          </cost>
          <time>
            <duration>
              <min>3686.0</min>
              <max>4122.0</max>
              <median>3719.0</median>
              <Q1>3690.0</Q1>
              <Q3>4055.0</Q3>
              <avg>3835.714285714286</avg>
              <total>26850.0</total>
            </duration>
            <waiting>
              <min>0.0</min>
              <max>0.0</max>
              <median>0.0</median>
              <Q1>0.0</Q1>
              <Q3>0.0</Q3>
              <avg>0.0</avg>
              <total>0.0</total>
            </waiting>
            <resources_idle>
              <min>0.0</min>
              <max>0.0</max>
              <median>0.0</median>
              <Q1>0.0</Q1>
              <Q3>0.0</Q3>
              <avg>0.0</avg>
              <total>0.0</total>
            </resources_idle>
          </time>
          <instances>
            <instance>
              <cost>0.0</cost>
              <time>
                <effective>3690</effective>
                <waiting>0</waiting>
                <resources_idle>0</resources_idle>
              </time>
            </instance>
            <instance>
              <cost>0.0</cost>
              <time>
                <effective>3719</effective>
                <waiting>0</waiting>
                <resources_idle>0</resources_idle>
              </time>
            </instance>
            <instance>
              <cost>0.0</cost>
              <time>
                <effective>4122</effective>
                <waiting>0</waiting>
                <resources_idle>0</resources_idle>
              </time>
            </instance>
            <instance>
              <cost>0.0</cost>
              <time>
                <effective>3705</effective>
                <waiting>0</waiting>
                <resources_idle>0</resources_idle>
              </time>
            </instance>
            <instance>
              <cost>0.0</cost>
              <time>
                <effective>3873</effective>
                <waiting>0</waiting>
                <resources_idle>0</resources_idle>
              </time>
            </instance>
            <instance>
              <cost>0.0</cost>
              <time>
                <effective>3686</effective>
                <waiting>0</waiting>
                <resources_idle>0</resources_idle>
              </time>
            </instance>
            <instance>
              <cost>0.0</cost>
              <time>
                <effective>4055</effective>
                <waiting>0</waiting>
                <resources_idle>0</resources_idle>
              </time>
            </instance>
          </instances>
        </activity>
        <activity>
          <id>9</id>
          <name>No Lumen</name>
          <cost>
            <min>0.0</min>
            <max>0.0</max>
            <median>0.0</median>
            <Q1>0.0</Q1>
            <Q3>0.0</Q3>
            <avg>0.0</avg>
            <total>0.0</total>
          </cost>
          <time>
            <duration>
              <min>2400.0</min>
              <max>2400.0</max>
              <median>2400.0</median>
              <Q1>2400.0</Q1>
              <Q3>2400.0</Q3>
              <avg>2400.0</avg>
              <total>7200.0</total>
            </duration>
            <waiting>
              <min>0.0</min>
              <max>0.0</max>
              <median>0.0</median>
              <Q1>0.0</Q1>
              <Q3>0.0</Q3>
              <avg>0.0</avg>
              <total>0.0</total>
            </waiting>
            <resources_idle>
              <min>0.0</min>
              <max>0.0</max>
              <median>0.0</median>
              <Q1>0.0</Q1>
              <Q3>0.0</Q3>
              <avg>0.0</avg>
              <total>0.0</total>
            </resources_idle>
          </time>
          <instances>
            <instance>
              <cost>0.0</cost>
              <time>
                <effective>2400</effective>
                <waiting>0</waiting>
                <resources_idle>0</resources_idle>
              </time>
            </instance>
            <instance>
              <cost>0.0</cost>
              <time>
                <effective>2400</effective>
                <waiting>0</waiting>
                <resources_idle>0</resources_idle>
              </time>
            </instance>
            <instance>
              <cost>0.0</cost>
              <time>
                <effective>2400</effective>
                <waiting>0</waiting>
                <resources_idle>0</resources_idle>
              </time>
            </instance>
          </instances>
        </activity>
        <activity>
          <id>60</id>
          <name>Carga de esterilizador liberada</name>
          <cost>
            <min>0.0</min>
            <max>4.166666666666666</max>
            <median>2.819444444444444</median>
            <Q1>2.083333333333333</Q1>
            <Q3>3.513888888888889</Q3>
            <avg>2.6934523809523805</avg>
            <total>75.41666666666666</total>
          </cost>
          <time>
            <duration>
              <min>0.0</min>
              <max>300.0</max>
              <median>203.0</median>
              <Q1>150.0</Q1>
              <Q3>253.0</Q3>
              <avg>193.92857142857142</avg>
              <total>5430.0</total>
            </duration>
            <waiting>
              <min>0.0</min>
              <max>0.0</max>
              <median>0.0</median>
              <Q1>0.0</Q1>
              <Q3>0.0</Q3>
              <avg>0.0</avg>
              <total>0.0</total>
            </waiting>
            <resources_idle>
              <min>0.0</min>
              <max>0.0</max>
              <median>0.0</median>
              <Q1>0.0</Q1>
              <Q3>0.0</Q3>
              <avg>0.0</avg>
              <total>0.0</total>
            </resources_idle>
          </time>
          <instances>
            <instance>
              <cost>2.847222222222222</cost>
              <time>
                <effective>205</effective>
                <waiting>0</waiting>
                <resources_idle>0</resources_idle>
              </time>
            </instance>
            <instance>
              <cost>3.319444444444444</cost>
              <time>
                <effective>239</effective>
                <waiting>0</waiting>
                <resources_idle>0</resources_idle>
              </time>
            </instance>
            <instance>
              <cost>3.5555555555555554</cost>
              <time>
                <effective>256</effective>
                <waiting>0</waiting>
                <resources_idle>0</resources_idle>
              </time>
            </instance>
            <instance>
              <cost>2.236111111111111</cost>
              <time>
                <effective>161</effective>
                <waiting>0</waiting>
                <resources_idle>0</resources_idle>
              </time>
            </instance>
            <instance>
              <cost>3.375</cost>
              <time>
                <effective>243</effective>
                <waiting>0</waiting>
                <resources_idle>0</resources_idle>
              </time>
            </instance>
            <instance>
              <cost>0.0</cost>
              <time>
                <effective>0</effective>
                <waiting>0</waiting>
                <resources_idle>0</resources_idle>
              </time>
            </instance>
            <instance>
              <cost>2.444444444444444</cost>
              <time>
                <effective>176</effective>
                <waiting>0</waiting>
                <resources_idle>0</resources_idle>
              </time>
            </instance>
            <instance>
              <cost>3.347222222222222</cost>
              <time>
                <effective>241</effective>
                <waiting>0</waiting>
                <resources_idle>0</resources_idle>
              </time>
            </instance>
            <instance>
              <cost>3.375</cost>
              <time>
                <effective>243</effective>
                <waiting>0</waiting>
                <resources_idle>0</resources_idle>
              </time>
            </instance>
            <instance>
              <cost>2.819444444444444</cost>
              <time>
                <effective>203</effective>
                <waiting>0</waiting>
                <resources_idle>0</resources_idle>
              </time>
            </instance>
            <instance>
              <cost>2.0</cost>
              <time>
                <effective>144</effective>
                <waiting>0</waiting>
                <resources_idle>0</resources_idle>
              </time>
            </instance>
            <instance>
              <cost>1.75</cost>
              <time>
                <effective>126</effective>
                <waiting>0</waiting>
                <resources_idle>0</resources_idle>
              </time>
            </instance>
            <instance>
              <cost>3.513888888888889</cost>
              <time>
                <effective>253</effective>
                <waiting>0</waiting>
                <resources_idle>0</resources_idle>
              </time>
            </instance>
            <instance>
              <cost>3.6666666666666665</cost>
              <time>
                <effective>264</effective>
                <waiting>0</waiting>
                <resources_idle>0</resources_idle>
              </time>
            </instance>
            <instance>
              <cost>0.0</cost>
              <time>
                <effective>0</effective>
                <waiting>0</waiting>
                <resources_idle>0</resources_idle>
              </time>
            </instance>
            <instance>
              <cost>2.236111111111111</cost>
              <time>
                <effective>161</effective>
                <waiting>0</waiting>
                <resources_idle>0</resources_idle>
              </time>
            </instance>
            <instance>
              <cost>3.6666666666666665</cost>
              <time>
                <effective>264</effective>
                <waiting>0</waiting>
                <resources_idle>0</resources_idle>
              </time>
            </instance>
            <instance>
              <cost>3.263888888888889</cost>
              <time>
                <effective>235</effective>
                <waiting>0</waiting>
                <resources_idle>0</resources_idle>
              </time>
            </instance>
            <instance>
              <cost>2.111111111111111</cost>
              <time>
                <effective>152</effective>
                <waiting>0</waiting>
                <resources_idle>0</resources_idle>
              </time>
            </instance>
            <instance>
              <cost>4.0</cost>
              <time>
                <effective>288</effective>
                <waiting>0</waiting>
                <resources_idle>0</resources_idle>
              </time>
            </instance>
            <instance>
              <cost>1.4444444444444444</cost>
              <time>
                <effective>104</effective>
                <waiting>0</waiting>
                <resources_idle>0</resources_idle>
              </time>
            </instance>
            <instance>
              <cost>4.166666666666666</cost>
              <time>
                <effective>300</effective>
                <waiting>0</waiting>
                <resources_idle>0</resources_idle>
              </time>
            </instance>
            <instance>
              <cost>4.166666666666666</cost>
              <time>
                <effective>300</effective>
                <waiting>0</waiting>
                <resources_idle>0</resources_idle>
              </time>
            </instance>
            <instance>
              <cost>1.7083333333333333</cost>
              <time>
                <effective>123</effective>
                <waiting>0</waiting>
                <resources_idle>0</resources_idle>
              </time>
            </instance>
            <instance>
              <cost>2.333333333333333</cost>
              <time>
                <effective>168</effective>
                <waiting>0</waiting>
                <resources_idle>0</resources_idle>
              </time>
            </instance>
            <instance>
              <cost>2.1527777777777777</cost>
              <time>
                <effective>155</effective>
                <waiting>0</waiting>
                <resources_idle>0</resources_idle>
              </time>
            </instance>
            <instance>
              <cost>3.833333333333333</cost>
              <time>
                <effective>276</effective>
                <waiting>0</waiting>
                <resources_idle>0</resources_idle>
              </time>
            </instance>
            <instance>
              <cost>2.083333333333333</cost>
              <time>
                <effective>150</effective>
                <waiting>0</waiting>
                <resources_idle>0</resources_idle>
              </time>
            </instance>
          </instances>
        </activity>
        <activity>
          <id>61</id>
          <name>Entrada Material Sucio</name>
          <cost>
            <min>0.0</min>
            <max>21.166666666666664</max>
            <median>12.458333333333332</median>
            <Q1>7.875</Q1>
            <Q3>18.930555555555554</Q3>
            <avg>12.992063492063494</avg>
            <total>363.7777777777778</total>
          </cost>
          <time>
            <duration>
              <min>0.0</min>
              <max>1524.0</max>
              <median>908.0</median>
              <Q1>567.0</Q1>
              <Q3>1363.0</Q3>
              <avg>956.8571428571429</avg>
              <total>26792.0</total>
            </duration>
            <waiting>
              <min>0.0</min>
              <max>0.0</max>
              <median>0.0</median>
              <Q1>0.0</Q1>
              <Q3>0.0</Q3>
              <avg>0.0</avg>
              <total>0.0</total>
            </waiting>
            <resources_idle>
              <min>0.0</min>
              <max>0.0</max>
              <median>0.0</median>
              <Q1>0.0</Q1>
              <Q3>0.0</Q3>
              <avg>0.0</avg>
              <total>0.0</total>
            </resources_idle>
          </time>
          <instances>
            <instance>
              <cost>21.166666666666664</cost>
              <time>
                <effective>1524</effective>
                <waiting>0</waiting>
                <resources_idle>0</resources_idle>
              </time>
            </instance>
            <instance>
              <cost>8.680555555555555</cost>
              <time>
                <effective>625</effective>
                <waiting>0</waiting>
                <resources_idle>0</resources_idle>
              </time>
            </instance>
            <instance>
              <cost>16.02777777777778</cost>
              <time>
                <effective>1154</effective>
                <waiting>0</waiting>
                <resources_idle>0</resources_idle>
              </time>
            </instance>
            <instance>
              <cost>0.0</cost>
              <time>
                <effective>0</effective>
                <waiting>0</waiting>
                <resources_idle>0</resources_idle>
              </time>
            </instance>
            <instance>
              <cost>18.930555555555554</cost>
              <time>
                <effective>1363</effective>
                <waiting>0</waiting>
                <resources_idle>0</resources_idle>
              </time>
            </instance>
            <instance>
              <cost>9.98611111111111</cost>
              <time>
                <effective>719</effective>
                <waiting>0</waiting>
                <resources_idle>0</resources_idle>
              </time>
            </instance>
            <instance>
              <cost>7.125</cost>
              <time>
                <effective>513</effective>
                <waiting>0</waiting>
                <resources_idle>0</resources_idle>
              </time>
            </instance>
            <instance>
              <cost>5.527777777777778</cost>
              <time>
                <effective>398</effective>
                <waiting>0</waiting>
                <resources_idle>0</resources_idle>
              </time>
            </instance>
            <instance>
              <cost>21.166666666666664</cost>
              <time>
                <effective>1524</effective>
                <waiting>0</waiting>
                <resources_idle>0</resources_idle>
              </time>
            </instance>
            <instance>
              <cost>15.638888888888888</cost>
              <time>
                <effective>1126</effective>
                <waiting>0</waiting>
                <resources_idle>0</resources_idle>
              </time>
            </instance>
            <instance>
              <cost>9.333333333333332</cost>
              <time>
                <effective>672</effective>
                <waiting>0</waiting>
                <resources_idle>0</resources_idle>
              </time>
            </instance>
            <instance>
              <cost>8.833333333333332</cost>
              <time>
                <effective>1236</effective>
                <waiting>0</waiting>
                <resources_idle>0</resources_idle>
              </time>
            </instance>
            <instance>
              <cost>5.291666666666666</cost>
              <time>
                <effective>381</effective>
                <waiting>0</waiting>
                <resources_idle>0</resources_idle>
              </time>
            </instance>
            <instance>
              <cost>3.6111111111111107</cost>
              <time>
                <effective>260</effective>
                <waiting>0</waiting>
                <resources_idle>0</resources_idle>
              </time>
            </instance>
            <instance>
              <cost>20.01388888888889</cost>
              <time>
                <effective>1441</effective>
                <waiting>0</waiting>
                <resources_idle>0</resources_idle>
              </time>
            </instance>
            <instance>
              <cost>7.875</cost>
              <time>
                <effective>567</effective>
                <waiting>0</waiting>
                <resources_idle>0</resources_idle>
              </time>
            </instance>
            <instance>
              <cost>17.902777777777775</cost>
              <time>
                <effective>1289</effective>
                <waiting>0</waiting>
                <resources_idle>0</resources_idle>
              </time>
            </instance>
            <instance>
              <cost>15.875</cost>
              <time>
                <effective>1143</effective>
                <waiting>0</waiting>
                <resources_idle>0</resources_idle>
              </time>
            </instance>
            <instance>
              <cost>21.125</cost>
              <time>
                <effective>1521</effective>
                <waiting>0</waiting>
                <resources_idle>0</resources_idle>
              </time>
            </instance>
            <instance>
              <cost>21.166666666666664</cost>
              <time>
                <effective>1524</effective>
                <waiting>0</waiting>
                <resources_idle>0</resources_idle>
              </time>
            </instance>
            <instance>
              <cost>12.458333333333332</cost>
              <time>
                <effective>897</effective>
                <waiting>0</waiting>
                <resources_idle>0</resources_idle>
              </time>
            </instance>
            <instance>
              <cost>7.722222222222221</cost>
              <time>
                <effective>556</effective>
                <waiting>0</waiting>
                <resources_idle>0</resources_idle>
              </time>
            </instance>
            <instance>
              <cost>8.11111111111111</cost>
              <time>
                <effective>584</effective>
                <waiting>0</waiting>
                <resources_idle>0</resources_idle>
              </time>
            </instance>
            <instance>
              <cost>9.98611111111111</cost>
              <time>
                <effective>719</effective>
                <waiting>0</waiting>
                <resources_idle>0</resources_idle>
              </time>
            </instance>
            <instance>
              <cost>21.166666666666664</cost>
              <time>
                <effective>1524</effective>
                <waiting>0</waiting>
                <resources_idle>0</resources_idle>
              </time>
            </instance>
            <instance>
              <cost>12.61111111111111</cost>
              <time>
                <effective>908</effective>
                <waiting>0</waiting>
                <resources_idle>0</resources_idle>
              </time>
            </instance>
            <instance>
              <cost>15.277777777777777</cost>
              <time>
                <effective>1100</effective>
                <waiting>0</waiting>
                <resources_idle>0</resources_idle>
              </time>
            </instance>
            <instance>
              <cost>21.166666666666664</cost>
              <time>
                <effective>1524</effective>
                <waiting>0</waiting>
                <resources_idle>0</resources_idle>
              </time>
            </instance>
          </instances>
        </activity>
        <activity>
          <id>72</id>
          <name>Carros</name>
          <cost>
            <min>0.0</min>
            <max>0.0</max>
            <median>0.0</median>
            <Q1>0.0</Q1>
            <Q3>0.0</Q3>
            <avg>0.0</avg>
            <total>0.0</total>
          </cost>
          <time>
            <duration>
              <min>2400.0</min>
              <max>2400.0</max>
              <median>2400.0</median>
              <Q1>2400.0</Q1>
              <Q3>2400.0</Q3>
              <avg>2400.0</avg>
              <total>7200.0</total>
            </duration>
            <waiting>
              <min>0.0</min>
              <max>0.0</max>
              <median>0.0</median>
              <Q1>0.0</Q1>
              <Q3>0.0</Q3>
              <avg>0.0</avg>
              <total>0.0</total>
            </waiting>
            <resources_idle>
              <min>0.0</min>
              <max>0.0</max>
              <median>0.0</median>
              <Q1>0.0</Q1>
              <Q3>0.0</Q3>
              <avg>0.0</avg>
              <total>0.0</total>
            </resources_idle>
          </time>
          <instances>
            <instance>
              <cost>0.0</cost>
              <time>
                <effective>2400</effective>
                <waiting>0</waiting>
                <resources_idle>0</resources_idle>
              </time>
            </instance>
            <instance>
              <cost>0.0</cost>
              <time>
                <effective>2400</effective>
                <waiting>0</waiting>
                <resources_idle>0</resources_idle>
              </time>
            </instance>
            <instance>
              <cost>0.0</cost>
              <time>
                <effective>2400</effective>
                <waiting>0</waiting>
                <resources_idle>0</resources_idle>
              </time>
            </instance>
          </instances>
        </activity>
        <activity>
          <id>62</id>
          <name>Cargado en carro L+D</name>
          <cost>
            <min>0.0</min>
            <max>17.61111111111111</max>
            <median>8.833333333333332</median>
            <Q1>1.722222222222222</Q1>
            <Q3>10.652777777777777</Q3>
            <avg>7.332837301587302</avg>
            <total>205.31944444444446</total>
          </cost>
          <time>
            <duration>
              <min>0.0</min>
              <max>1268.0</max>
              <median>636.0</median>
              <Q1>124.0</Q1>
              <Q3>767.0</Q3>
              <avg>527.9642857142857</avg>
              <total>14783.0</total>
            </duration>
            <waiting>
              <min>0.0</min>
              <max>0.0</max>
              <median>0.0</median>
              <Q1>0.0</Q1>
              <Q3>0.0</Q3>
              <avg>0.0</avg>
              <total>0.0</total>
            </waiting>
            <resources_idle>
              <min>0.0</min>
              <max>0.0</max>
              <median>0.0</median>
              <Q1>0.0</Q1>
              <Q3>0.0</Q3>
              <avg>0.0</avg>
              <total>0.0</total>
            </resources_idle>
          </time>
          <instances>
            <instance>
              <cost>10.652777777777777</cost>
              <time>
                <effective>767</effective>
                <waiting>0</waiting>
                <resources_idle>0</resources_idle>
              </time>
            </instance>
            <instance>
              <cost>0.0</cost>
              <time>
                <effective>0</effective>
                <waiting>0</waiting>
                <resources_idle>0</resources_idle>
              </time>
            </instance>
            <instance>
              <cost>2.5</cost>
              <time>
                <effective>180</effective>
                <waiting>0</waiting>
                <resources_idle>0</resources_idle>
              </time>
            </instance>
            <instance>
              <cost>9.555555555555555</cost>
              <time>
                <effective>688</effective>
                <waiting>0</waiting>
                <resources_idle>0</resources_idle>
              </time>
            </instance>
            <instance>
              <cost>0.0</cost>
              <time>
                <effective>0</effective>
                <waiting>0</waiting>
                <resources_idle>0</resources_idle>
              </time>
            </instance>
            <instance>
              <cost>12.347222222222221</cost>
              <time>
                <effective>889</effective>
                <waiting>0</waiting>
                <resources_idle>0</resources_idle>
              </time>
            </instance>
            <instance>
              <cost>10.416666666666666</cost>
              <time>
                <effective>750</effective>
                <waiting>0</waiting>
                <resources_idle>0</resources_idle>
              </time>
            </instance>
            <instance>
              <cost>1.0</cost>
              <time>
                <effective>72</effective>
                <waiting>0</waiting>
                <resources_idle>0</resources_idle>
              </time>
            </instance>
            <instance>
              <cost>0.0</cost>
              <time>
                <effective>0</effective>
                <waiting>0</waiting>
                <resources_idle>0</resources_idle>
              </time>
            </instance>
            <instance>
              <cost>9.194444444444445</cost>
              <time>
                <effective>662</effective>
                <waiting>0</waiting>
                <resources_idle>0</resources_idle>
              </time>
            </instance>
            <instance>
              <cost>3.125</cost>
              <time>
                <effective>225</effective>
                <waiting>0</waiting>
                <resources_idle>0</resources_idle>
              </time>
            </instance>
            <instance>
              <cost>17.61111111111111</cost>
              <time>
                <effective>1268</effective>
                <waiting>0</waiting>
                <resources_idle>0</resources_idle>
              </time>
            </instance>
            <instance>
              <cost>0.0</cost>
              <time>
                <effective>0</effective>
                <waiting>0</waiting>
                <resources_idle>0</resources_idle>
              </time>
            </instance>
            <instance>
              <cost>3.75</cost>
              <time>
                <effective>270</effective>
                <waiting>0</waiting>
                <resources_idle>0</resources_idle>
              </time>
            </instance>
            <instance>
              <cost>13.388888888888888</cost>
              <time>
                <effective>964</effective>
                <waiting>0</waiting>
                <resources_idle>0</resources_idle>
              </time>
            </instance>
            <instance>
              <cost>11.36111111111111</cost>
              <time>
                <effective>818</effective>
                <waiting>0</waiting>
                <resources_idle>0</resources_idle>
              </time>
            </instance>
            <instance>
              <cost>1.722222222222222</cost>
              <time>
                <effective>124</effective>
                <waiting>0</waiting>
                <resources_idle>0</resources_idle>
              </time>
            </instance>
            <instance>
              <cost>9.402777777777777</cost>
              <time>
                <effective>677</effective>
                <waiting>0</waiting>
                <resources_idle>0</resources_idle>
              </time>
            </instance>
            <instance>
              <cost>14.5</cost>
              <time>
                <effective>1044</effective>
                <waiting>0</waiting>
                <resources_idle>0</resources_idle>
              </time>
            </instance>
            <instance>
              <cost>14.458333333333332</cost>
              <time>
                <effective>1041</effective>
                <waiting>0</waiting>
                <resources_idle>0</resources_idle>
              </time>
            </instance>
            <instance>
              <cost>1.5694444444444444</cost>
              <time>
                <effective>113</effective>
                <waiting>0</waiting>
                <resources_idle>0</resources_idle>
              </time>
            </instance>
            <instance>
              <cost>6.125</cost>
              <time>
                <effective>441</effective>
                <waiting>0</waiting>
                <resources_idle>0</resources_idle>
              </time>
            </instance>
            <instance>
              <cost>10.416666666666666</cost>
              <time>
                <effective>750</effective>
                <waiting>0</waiting>
                <resources_idle>0</resources_idle>
              </time>
            </instance>
            <instance>
              <cost>1.9583333333333333</cost>
              <time>
                <effective>141</effective>
                <waiting>0</waiting>
                <resources_idle>0</resources_idle>
              </time>
            </instance>
            <instance>
              <cost>14.5</cost>
              <time>
                <effective>1044</effective>
                <waiting>0</waiting>
                <resources_idle>0</resources_idle>
              </time>
            </instance>
            <instance>
              <cost>8.833333333333332</cost>
              <time>
                <effective>636</effective>
                <waiting>0</waiting>
                <resources_idle>0</resources_idle>
              </time>
            </instance>
            <instance>
              <cost>10.652777777777777</cost>
              <time>
                <effective>767</effective>
                <waiting>0</waiting>
                <resources_idle>0</resources_idle>
              </time>
            </instance>
            <instance>
              <cost>6.277777777777778</cost>
              <time>
                <effective>452</effective>
                <waiting>0</waiting>
                <resources_idle>0</resources_idle>
              </time>
            </instance>
          </instances>
        </activity>
        <activity>
          <id>63</id>
          <name>Carga L+D iniciada</name>
          <cost>
            <min>0.0</min>
            <max>6.180555555555555</max>
            <median>3.444444444444444</median>
            <Q1>2.347222222222222</Q1>
            <Q3>4.5</Q3>
            <avg>3.5376984126984135</avg>
            <total>99.05555555555557</total>
          </cost>
          <time>
            <duration>
              <min>0.0</min>
              <max>445.0</max>
              <median>248.0</median>
              <Q1>169.0</Q1>
              <Q3>324.0</Q3>
              <avg>254.71428571428572</avg>
              <total>7132.0</total>
            </duration>
            <waiting>
              <min>0.0</min>
              <max>0.0</max>
              <median>0.0</median>
              <Q1>0.0</Q1>
              <Q3>0.0</Q3>
              <avg>0.0</avg>
              <total>0.0</total>
            </waiting>
            <resources_idle>
              <min>0.0</min>
              <max>0.0</max>
              <median>0.0</median>
              <Q1>0.0</Q1>
              <Q3>0.0</Q3>
              <avg>0.0</avg>
              <total>0.0</total>
            </resources_idle>
          </time>
          <instances>
            <instance>
              <cost>5.430555555555555</cost>
              <time>
                <effective>391</effective>
                <waiting>0</waiting>
                <resources_idle>0</resources_idle>
              </time>
            </instance>
            <instance>
              <cost>1.736111111111111</cost>
              <time>
                <effective>125</effective>
                <waiting>0</waiting>
                <resources_idle>0</resources_idle>
              </time>
            </instance>
            <instance>
              <cost>4.236111111111111</cost>
              <time>
                <effective>305</effective>
                <waiting>0</waiting>
                <resources_idle>0</resources_idle>
              </time>
            </instance>
            <instance>
              <cost>2.1666666666666665</cost>
              <time>
                <effective>156</effective>
                <waiting>0</waiting>
                <resources_idle>0</resources_idle>
              </time>
            </instance>
            <instance>
              <cost>0.0</cost>
              <time>
                <effective>0</effective>
                <waiting>0</waiting>
                <resources_idle>0</resources_idle>
              </time>
            </instance>
            <instance>
              <cost>2.5277777777777777</cost>
              <time>
                <effective>182</effective>
                <waiting>0</waiting>
                <resources_idle>0</resources_idle>
              </time>
            </instance>
            <instance>
              <cost>4.444444444444445</cost>
              <time>
                <effective>320</effective>
                <waiting>0</waiting>
                <resources_idle>0</resources_idle>
              </time>
            </instance>
            <instance>
              <cost>1.7916666666666665</cost>
              <time>
                <effective>129</effective>
                <waiting>0</waiting>
                <resources_idle>0</resources_idle>
              </time>
            </instance>
            <instance>
              <cost>4.916666666666666</cost>
              <time>
                <effective>354</effective>
                <waiting>0</waiting>
                <resources_idle>0</resources_idle>
              </time>
            </instance>
            <instance>
              <cost>2.6805555555555554</cost>
              <time>
                <effective>193</effective>
                <waiting>0</waiting>
                <resources_idle>0</resources_idle>
              </time>
            </instance>
            <instance>
              <cost>4.152777777777778</cost>
              <time>
                <effective>299</effective>
                <waiting>0</waiting>
                <resources_idle>0</resources_idle>
              </time>
            </instance>
            <instance>
              <cost>1.347222222222222</cost>
              <time>
                <effective>97</effective>
                <waiting>0</waiting>
                <resources_idle>0</resources_idle>
              </time>
            </instance>
            <instance>
              <cost>6.180555555555555</cost>
              <time>
                <effective>445</effective>
                <waiting>0</waiting>
                <resources_idle>0</resources_idle>
              </time>
            </instance>
            <instance>
              <cost>4.5</cost>
              <time>
                <effective>324</effective>
                <waiting>0</waiting>
                <resources_idle>0</resources_idle>
              </time>
            </instance>
            <instance>
              <cost>5.166666666666666</cost>
              <time>
                <effective>372</effective>
                <waiting>0</waiting>
                <resources_idle>0</resources_idle>
              </time>
            </instance>
            <instance>
              <cost>5.416666666666666</cost>
              <time>
                <effective>390</effective>
                <waiting>0</waiting>
                <resources_idle>0</resources_idle>
              </time>
            </instance>
            <instance>
              <cost>2.347222222222222</cost>
              <time>
                <effective>169</effective>
                <waiting>0</waiting>
                <resources_idle>0</resources_idle>
              </time>
            </instance>
            <instance>
              <cost>4.194444444444445</cost>
              <time>
                <effective>302</effective>
                <waiting>0</waiting>
                <resources_idle>0</resources_idle>
              </time>
            </instance>
            <instance>
              <cost>2.833333333333333</cost>
              <time>
                <effective>204</effective>
                <waiting>0</waiting>
                <resources_idle>0</resources_idle>
              </time>
            </instance>
            <instance>
              <cost>3.4027777777777777</cost>
              <time>
                <effective>245</effective>
                <waiting>0</waiting>
                <resources_idle>0</resources_idle>
              </time>
            </instance>
            <instance>
              <cost>2.3055555555555554</cost>
              <time>
                <effective>166</effective>
                <waiting>0</waiting>
                <resources_idle>0</resources_idle>
              </time>
            </instance>
            <instance>
              <cost>2.4027777777777777</cost>
              <time>
                <effective>173</effective>
                <waiting>0</waiting>
                <resources_idle>0</resources_idle>
              </time>
            </instance>
            <instance>
              <cost>4.444444444444445</cost>
              <time>
                <effective>320</effective>
                <waiting>0</waiting>
                <resources_idle>0</resources_idle>
              </time>
            </instance>
            <instance>
              <cost>2.833333333333333</cost>
              <time>
                <effective>204</effective>
                <waiting>0</waiting>
                <resources_idle>0</resources_idle>
              </time>
            </instance>
            <instance>
              <cost>4.666666666666666</cost>
              <time>
                <effective>336</effective>
                <waiting>0</waiting>
                <resources_idle>0</resources_idle>
              </time>
            </instance>
            <instance>
              <cost>4.055555555555555</cost>
              <time>
                <effective>292</effective>
                <waiting>0</waiting>
                <resources_idle>0</resources_idle>
              </time>
            </instance>
            <instance>
              <cost>5.430555555555555</cost>
              <time>
                <effective>391</effective>
                <waiting>0</waiting>
                <resources_idle>0</resources_idle>
              </time>
            </instance>
            <instance>
              <cost>3.444444444444444</cost>
              <time>
                <effective>248</effective>
                <waiting>0</waiting>
                <resources_idle>0</resources_idle>
              </time>
            </instance>
          </instances>
        </activity>
        <activity>
          <id>76</id>
          <name>Carga L+D liberada</name>
          <cost>
            <min>0.0</min>
            <max>6.527777777777778</max>
            <median>3.319444444444444</median>
            <Q1>2.0416666666666665</Q1>
            <Q3>4.555555555555555</Q3>
            <avg>3.4573412698412693</avg>
            <total>96.80555555555554</total>
          </cost>
          <time>
            <duration>
              <min>0.0</min>
              <max>470.0</max>
              <median>239.0</median>
              <Q1>147.0</Q1>
              <Q3>328.0</Q3>
              <avg>248.92857142857142</avg>
              <total>6970.0</total>
            </duration>
            <waiting>
              <min>0.0</min>
              <max>0.0</max>
              <median>0.0</median>
              <Q1>0.0</Q1>
              <Q3>0.0</Q3>
              <avg>0.0</avg>
              <total>0.0</total>
            </waiting>
            <resources_idle>
              <min>0.0</min>
              <max>0.0</max>
              <median>0.0</median>
              <Q1>0.0</Q1>
              <Q3>0.0</Q3>
              <avg>0.0</avg>
              <total>0.0</total>
            </resources_idle>
          </time>
          <instances>
            <instance>
              <cost>5.625</cost>
              <time>
                <effective>405</effective>
                <waiting>0</waiting>
                <resources_idle>0</resources_idle>
              </time>
            </instance>
            <instance>
              <cost>2.611111111111111</cost>
              <time>
                <effective>188</effective>
                <waiting>0</waiting>
                <resources_idle>0</resources_idle>
              </time>
            </instance>
            <instance>
              <cost>2.0416666666666665</cost>
              <time>
                <effective>147</effective>
                <waiting>0</waiting>
                <resources_idle>0</resources_idle>
              </time>
            </instance>
            <instance>
              <cost>4.208333333333333</cost>
              <time>
                <effective>303</effective>
                <waiting>0</waiting>
                <resources_idle>0</resources_idle>
              </time>
            </instance>
            <instance>
              <cost>5.333333333333333</cost>
              <time>
                <effective>384</effective>
                <waiting>0</waiting>
                <resources_idle>0</resources_idle>
              </time>
            </instance>
            <instance>
              <cost>2.0972222222222223</cost>
              <time>
                <effective>151</effective>
                <waiting>0</waiting>
                <resources_idle>0</resources_idle>
              </time>
            </instance>
            <instance>
              <cost>4.486111111111111</cost>
              <time>
                <effective>323</effective>
                <waiting>0</waiting>
                <resources_idle>0</resources_idle>
              </time>
            </instance>
            <instance>
              <cost>4.041666666666666</cost>
              <time>
                <effective>291</effective>
                <waiting>0</waiting>
                <resources_idle>0</resources_idle>
              </time>
            </instance>
            <instance>
              <cost>2.0</cost>
              <time>
                <effective>144</effective>
                <waiting>0</waiting>
                <resources_idle>0</resources_idle>
              </time>
            </instance>
            <instance>
              <cost>3.2777777777777777</cost>
              <time>
                <effective>236</effective>
                <waiting>0</waiting>
                <resources_idle>0</resources_idle>
              </time>
            </instance>
            <instance>
              <cost>5.638888888888888</cost>
              <time>
                <effective>406</effective>
                <waiting>0</waiting>
                <resources_idle>0</resources_idle>
              </time>
            </instance>
            <instance>
              <cost>0.0</cost>
              <time>
                <effective>0</effective>
                <waiting>0</waiting>
                <resources_idle>0</resources_idle>
              </time>
            </instance>
            <instance>
              <cost>2.611111111111111</cost>
              <time>
                <effective>188</effective>
                <waiting>0</waiting>
                <resources_idle>0</resources_idle>
              </time>
            </instance>
            <instance>
              <cost>3.319444444444444</cost>
              <time>
                <effective>239</effective>
                <waiting>0</waiting>
                <resources_idle>0</resources_idle>
              </time>
            </instance>
            <instance>
              <cost>4.75</cost>
              <time>
                <effective>342</effective>
                <waiting>0</waiting>
                <resources_idle>0</resources_idle>
              </time>
            </instance>
            <instance>
              <cost>1.3333333333333333</cost>
              <time>
                <effective>96</effective>
                <waiting>0</waiting>
                <resources_idle>0</resources_idle>
              </time>
            </instance>
            <instance>
              <cost>1.8333333333333333</cost>
              <time>
                <effective>132</effective>
                <waiting>0</waiting>
                <resources_idle>0</resources_idle>
              </time>
            </instance>
            <instance>
              <cost>2.25</cost>
              <time>
                <effective>162</effective>
                <waiting>0</waiting>
                <resources_idle>0</resources_idle>
              </time>
            </instance>
            <instance>
              <cost>4.486111111111111</cost>
              <time>
                <effective>323</effective>
                <waiting>0</waiting>
                <resources_idle>0</resources_idle>
              </time>
            </instance>
            <instance>
              <cost>1.4027777777777777</cost>
              <time>
                <effective>101</effective>
                <waiting>0</waiting>
                <resources_idle>0</resources_idle>
              </time>
            </instance>
            <instance>
              <cost>4.25</cost>
              <time>
                <effective>306</effective>
                <waiting>0</waiting>
                <resources_idle>0</resources_idle>
              </time>
            </instance>
            <instance>
              <cost>5.041666666666666</cost>
              <time>
                <effective>363</effective>
                <waiting>0</waiting>
                <resources_idle>0</resources_idle>
              </time>
            </instance>
            <instance>
              <cost>5.638888888888888</cost>
              <time>
                <effective>406</effective>
                <waiting>0</waiting>
                <resources_idle>0</resources_idle>
              </time>
            </instance>
            <instance>
              <cost>4.138888888888888</cost>
              <time>
                <effective>298</effective>
                <waiting>0</waiting>
                <resources_idle>0</resources_idle>
              </time>
            </instance>
            <instance>
              <cost>2.4305555555555554</cost>
              <time>
                <effective>175</effective>
                <waiting>0</waiting>
                <resources_idle>0</resources_idle>
              </time>
            </instance>
            <instance>
              <cost>0.875</cost>
              <time>
                <effective>63</effective>
                <waiting>0</waiting>
                <resources_idle>0</resources_idle>
              </time>
            </instance>
            <instance>
              <cost>4.555555555555555</cost>
              <time>
                <effective>328</effective>
                <waiting>0</waiting>
                <resources_idle>0</resources_idle>
              </time>
            </instance>
            <instance>
              <cost>6.527777777777778</cost>
              <time>
                <effective>470</effective>
                <waiting>0</waiting>
                <resources_idle>0</resources_idle>
              </time>
            </instance>
          </instances>
        </activity>
      </activities>
    </process>
  </processes>
  <resources>
    <resource>
      <type>Jupiter</type>
      <cost>
        <min>0.0</min>
        <max>0.0</max>
        <median>0.0</median>
        <Q1>0.0</Q1>
        <Q3>0.0</Q3>
        <avg>0.0</avg>
        <total>0.0</total>
      </cost>
      <time>
        <in_use>
          <min>7200.0</min>
          <max>7200.0</max>
          <median>7200.0</median>
          <Q1>7200.0</Q1>
          <Q3>7200.0</Q3>
          <avg>7200.0</avg>
          <total>7200.0</total>
        </in_use>
        <available>
          <min>122436.0</min>
          <max>122436.0</max>
          <median>122436.0</median>
          <Q1>122436.0</Q1>
          <Q3>122436.0</Q3>
          <avg>122436.0</avg>
          <total>122436.0</total>
        </available>
        <workload>
          <min>0.058806233460746836</min>
          <max>0.058806233460746836</max>
          <median>0.058806233460746836</median>
          <Q1>0.058806233460746836</Q1>
          <Q3>0.058806233460746836</Q3>
          <avg>0.058806233460746836</avg>
          <total>0.058806233460746836</total>
        </workload>
      </time>
      <instances>
        <instance>
          <id>#0</id>
          <cost>0.0</cost>
          <time>
            <in_use>7200</in_use>
            <available>122436</available>
            <workload>0.058806233460746836</workload>
          </time>
        </instance>
      </instances>
    </resource>
    <resource>
      <type>Usuario</type>
      <cost>
        <min>600.5</min>
        <max>1700.5</max>
        <median>600.5</median>
        <Q1>600.5</Q1>
        <Q3>1700.5</Q3>
        <avg>1150.5</avg>
        <total>2301.0</total>
      </cost>
      <time>
        <in_use>
          <min>23528.0</min>
          <max>27719.0</max>
          <median>23528.0</median>
          <Q1>23528.0</Q1>
          <Q3>27719.0</Q3>
          <avg>25623.5</avg>
          <total>51247.0</total>
        </in_use>
        <available>
          <min>43236.0</min>
          <max>122436.0</max>
          <median>43236.0</median>
          <Q1>43236.0</Q1>
          <Q3>122436.0</Q3>
          <avg>82836.0</avg>
          <total>165672.0</total>
        </available>
        <workload>
          <min>0.19216570289784052</min>
          <max>0.6411092608011842</max>
          <median>0.19216570289784052</median>
          <Q1>0.19216570289784052</Q1>
          <Q3>0.6411092608011842</Q3>
          <avg>0.4166374818495124</avg>
          <total>0.8332749636990248</total>
        </workload>
      </time>
      <instances>
        <instance>
          <id>AV</id>
          <cost>1700.5</cost>
          <time>
            <in_use>23528</in_use>
            <available>122436</available>
            <workload>0.19216570289784052</workload>
          </time>
        </instance>
        <instance>
          <id>BM</id>
          <cost>600.5</cost>
          <time>
            <in_use>27719</in_use>
            <available>43236</available>
            <workload>0.6411092608011842</workload>
          </time>
        </instance>
      </instances>
    </resource>
    <resource>
      <type>Autoclave</type>
      <cost>
        <min>0.0</min>
        <max>0.0</max>
        <median>0.0</median>
        <Q1>0.0</Q1>
        <Q3>0.0</Q3>
        <avg>0.0</avg>
        <total>0.0</total>
      </cost>
      <time>
        <in_use>
          <min>19413.0</min>
          <max>30170.0</max>
          <median>20159.0</median>
          <Q1>19413.0</Q1>
          <Q3>27287.0</Q3>
          <avg>24257.25</avg>
          <total>97029.0</total>
        </in_use>
        <available>
          <min>122436.0</min>
          <max>122436.0</max>
          <median>122436.0</median>
          <Q1>122436.0</Q1>
          <Q3>122436.0</Q3>
          <avg>122436.0</avg>
          <total>489744.0</total>
        </available>
        <workload>
          <min>0.15855630696853867</min>
          <max>0.24641445326537947</max>
          <median>0.16464928615766605</median>
          <Q1>0.15855630696853867</Q1>
          <Q3>0.22286745728380541</Q3>
          <avg>0.19812187591884742</avg>
          <total>0.7924875036753897</total>
        </workload>
      </time>
      <instances>
        <instance>
          <id>#3</id>
          <cost>0.0</cost>
          <time>
            <in_use>19413</in_use>
            <available>122436</available>
            <workload>0.15855630696853867</workload>
          </time>
        </instance>
        <instance>
          <id>#0</id>
          <cost>0.0</cost>
          <time>
            <in_use>27287</in_use>
            <available>122436</available>
            <workload>0.22286745728380541</workload>
          </time>
        </instance>
        <instance>
          <id>#1</id>
          <cost>0.0</cost>
          <time>
            <in_use>30170</in_use>
            <available>122436</available>
            <workload>0.24641445326537947</workload>
          </time>
        </instance>
        <instance>
          <id>#2</id>
          <cost>0.0</cost>
          <time>
            <in_use>20159</in_use>
            <available>122436</available>
            <workload>0.16464928615766605</workload>
          </time>
        </instance>
      </instances>
    </resource>
    <resource>
      <type>Lavadora</type>
      <cost>
        <min>0.0</min>
        <max>0.0</max>
        <median>0.0</median>
        <Q1>0.0</Q1>
        <Q3>0.0</Q3>
        <avg>0.0</avg>
        <total>0.0</total>
      </cost>
      <time>
        <in_use>
          <min>10800.0</min>
          <max>25200.0</max>
          <median>21600.0</median>
          <Q1>10800.0</Q1>
          <Q3>21600.0</Q3>
          <avg>19800.0</avg>
          <total>79200.0</total>
        </in_use>
        <available>
          <min>122436.0</min>
          <max>122436.0</max>
          <median>122436.0</median>
          <Q1>122436.0</Q1>
          <Q3>122436.0</Q3>
          <avg>122436.0</avg>
          <total>489744.0</total>
        </available>
        <workload>
          <min>0.08820935019112026</min>
          <max>0.20582181711261394</max>
          <median>0.17641870038224053</median>
          <Q1>0.08820935019112026</Q1>
          <Q3>0.17641870038224053</Q3>
          <avg>0.1617171420170538</avg>
          <total>0.6468685680682152</total>
        </workload>
      </time>
      <instances>
        <instance>
          <id>#3</id>
          <cost>0.0</cost>
          <time>
            <in_use>10800</in_use>
            <available>122436</available>
            <workload>0.08820935019112026</workload>
          </time>
        </instance>
        <instance>
          <id>#0</id>
          <cost>0.0</cost>
          <time>
            <in_use>25200</in_use>
            <available>122436</available>
            <workload>0.20582181711261394</workload>
          </time>
        </instance>
        <instance>
          <id>#1</id>
          <cost>0.0</cost>
          <time>
            <in_use>21600</in_use>
            <available>122436</available>
            <workload>0.17641870038224053</workload>
          </time>
        </instance>
        <instance>
          <id>#2</id>
          <cost>0.0</cost>
          <time>
            <in_use>21600</in_use>
            <available>122436</available>
            <workload>0.17641870038224053</workload>
          </time>
        </instance>
      </instances>
    </resource>
    <resource>
      <type>VPro</type>
      <cost>
        <min>0.0</min>
        <max>0.0</max>
        <median>0.0</median>
        <Q1>0.0</Q1>
        <Q3>0.0</Q3>
        <avg>0.0</avg>
        <total>0.0</total>
      </cost>
      <time>
        <in_use>
          <min>7200.0</min>
          <max>7200.0</max>
          <median>7200.0</median>
          <Q1>7200.0</Q1>
          <Q3>7200.0</Q3>
          <avg>7200.0</avg>
          <total>7200.0</total>
        </in_use>
        <available>
          <min>122436.0</min>
          <max>122436.0</max>
          <median>122436.0</median>
          <Q1>122436.0</Q1>
          <Q3>122436.0</Q3>
          <avg>122436.0</avg>
          <total>122436.0</total>
        </available>
        <workload>
          <min>0.058806233460746836</min>
          <max>0.058806233460746836</max>
          <median>0.058806233460746836</median>
          <Q1>0.058806233460746836</Q1>
          <Q3>0.058806233460746836</Q3>
          <avg>0.058806233460746836</avg>
          <total>0.058806233460746836</total>
        </workload>
      </time>
      <instances>
        <instance>
          <id>#0</id>
          <cost>0.0</cost>
          <time>
            <in_use>7200</in_use>
            <available>122436</available>
            <workload>0.058806233460746836</workload>
          </time>
        </instance>
      </instances>
    </resource>
  </resources>
</resourceUtilization>
